neuralnetrag-0.1.2.dist-info/METADATA
neuralnetrag-0.1.2.dist-info/WHEEL
neuralnetrag/__init__.py
neuralnetrag/neuralnetrag.cp311-win_amd64.pyd
neuralnetrag-0.1.2.dist-info/RECORD
