Metadata-Version: 2.3
Name: neuralnetrag
Version: 0.1.2
